{"product_name":"B003JVCA9Q","avg_rating":3.6373626373626373}
{"product_name":"B00354NAYG","avg_rating":3.6363636363636362}
{"product_name":"B00CF7KVGE","avg_rating":3.6363636363636362}
{"product_name":"B0043B5SLI","avg_rating":3.6363636363636362}
{"product_name":"B0023CBY4E","avg_rating":3.6363636363636362}
{"product_name":"B00005O0I7","avg_rating":3.6315789473684212}
{"product_name":"B00HD4R5YU","avg_rating":3.625}
{"product_name":"B000WMEEAI","avg_rating":3.625}
{"product_name":"B002BRZ744","avg_rating":3.625}
{"product_name":"B00CMQTVUA","avg_rating":3.619718309859155}
{"product_name":"B0012N746W","avg_rating":3.619047619047619}
{"product_name":"B001CM0PR8","avg_rating":3.619047619047619}
