{"product_name":"B0018BELN2","avg_rating":4.3478260869565215}
{"product_name":"B0041OWQUI","avg_rating":4.3478260869565215}
{"product_name":"B00BGA9X9W","avg_rating":4.346153846153846}
{"product_name":"B002I0GX88","avg_rating":4.345454545454546}
{"product_name":"B0038MUCPK","avg_rating":4.344827586206897}
{"product_name":"B00BGA9WK2","avg_rating":4.342465753424658}
{"product_name":"B00006IR62","avg_rating":4.342105263157895}
{"product_name":"B003ZHMMEM","avg_rating":4.338983050847458}
{"product_name":"B003O6HAS2","avg_rating":4.333333333333333}
{"product_name":"B00434FED2","avg_rating":4.333333333333333}
{"product_name":"B000A0EFJW","avg_rating":4.333333333333333}
{"product_name":"B000TT4GBG","avg_rating":4.333333333333333}
{"product_name":"B000021Y5P","avg_rating":4.333333333333333}
{"product_name":"B0000AI1KK","avg_rating":4.333333333333333}
{"product_name":"B000E49SGE","avg_rating":4.333333333333333}
{"product_name":"B003H0CBYS","avg_rating":4.333333333333333}
{"product_name":"B00002NDRY","avg_rating":4.333333333333333}
{"product_name":"B0002CHIWO","avg_rating":4.333333333333333}
{"product_name":"B000641ZBI","avg_rating":4.333333333333333}
{"product_name":"B00020BV1A","avg_rating":4.333333333333333}
{"product_name":"B006JKAS16","avg_rating":4.333333333333333}
{"product_name":"B00009ZVHR","avg_rating":4.333333333333333}
{"product_name":"B00B59L9T6","avg_rating":4.333333333333333}
{"product_name":"B00008H2IU","avg_rating":4.333333333333333}
{"product_name":"B000B9RI00","avg_rating":4.333333333333333}
{"product_name":"B008277M36","avg_rating":4.333333333333333}
{"product_name":"B001TOQ8K2","avg_rating":4.333333333333333}
{"product_name":"B0007P8FN2","avg_rating":4.333333333333333}
{"product_name":"B002I0EH6I","avg_rating":4.333333333333333}
{"product_name":"B002I0KP4G","avg_rating":4.333333333333333}
{"product_name":"B00004U4R9","avg_rating":4.333333333333333}
{"product_name":"B000056O4Q","avg_rating":4.333333333333333}
{"product_name":"B000HEB3UU","avg_rating":4.333333333333333}
{"product_name":"B00GZ1GUNO","avg_rating":4.333333333333333}
{"product_name":"B00BDS415I","avg_rating":4.333333333333333}
{"product_name":"B000N0WBL8","avg_rating":4.333333333333333}
{"product_name":"B000WS97QI","avg_rating":4.333333333333333}
