{"product_name":"B00005O0I2","avg_rating":4.673469387755102}
{"product_name":"B000E0OCR8","avg_rating":4.666666666666667}
{"product_name":"B001H4NMNA","avg_rating":4.666666666666667}
{"product_name":"B001BX6JUA","avg_rating":4.666666666666667}
{"product_name":"B00009WAUL","avg_rating":4.666666666666667}
{"product_name":"B000FJSIUA","avg_rating":4.666666666666667}
{"product_name":"B00CJ7IUIQ","avg_rating":4.666666666666667}
{"product_name":"B00019HNNC","avg_rating":4.666666666666667}
{"product_name":"B00002SVG2","avg_rating":4.666666666666667}
{"product_name":"B000090W86","avg_rating":4.666666666666667}
{"product_name":"B000Z9A95M","avg_rating":4.666666666666667}
{"product_name":"B00008KU9Z","avg_rating":4.666666666666667}
{"product_name":"Microsoft Xbox 360 Controller for Windows","avg_rating":4.666666666666667}
{"product_name":"B00030GS8A","avg_rating":4.666666666666667}
{"product_name":"B00004UE0V","avg_rating":4.666666666666667}
{"product_name":"B00007KUUD","avg_rating":4.666666666666667}
